liveproxy/__init__.py
liveproxy/argparser.py
liveproxy/main.py
liveproxy/server.py
liveproxy_fork-3.0.0.dist-info/METADATA
liveproxy_fork-3.0.0.dist-info/WHEEL
liveproxy_fork-3.0.0.dist-info/entry_points.txt
liveproxy_fork-3.0.0.dist-info/top_level.txt
liveproxy_fork-3.0.0.dist-info/RECORD
