Metadata-Version: 2.4
Name: liveproxy-fork
Version: 3.0.0
Summary: LiveProxy can redirect Livestreams to your favorite player
Home-page: https://github.com/amjiddader/liveproxy
Author: amjiddader
Author-email: amjiddader@gmail.com
Project-URL: Source, https://github.com/amjiddader/liveproxy/
Project-URL: Tracker, https://github.com/back-to/liveproxy/issues
Keywords: LiveProxy Streamlink Youtube-DL YT-DLP
Classifier: Development Status :: 4 - Beta
Classifier: Environment :: Console
Classifier: Programming Language :: Python :: 3
Classifier: Programming Language :: Python
Classifier: Topic :: Internet :: WWW/HTTP
Classifier: Topic :: Multimedia :: Video
Requires-Python: >=3.6, <4
Dynamic: author
Dynamic: author-email
Dynamic: classifier
Dynamic: description
Dynamic: description-content-type
Dynamic: home-page
Dynamic: keywords
Dynamic: project-url
Dynamic: requires-python
Dynamic: summary
